[
    {
        "host": "49.7.253.214",
        "port": 443
    },
    {
        "host": "49.7.253.88",
        "port": 80
    },
    {
        "host": "msfwifi.3g.qq.com",
        "port": 8080
    },
    {
        "host": "183.47.117.157",
        "port": 14000
    },
    {
        "host": "49.7.253.220",
        "port": 443
    },
    {
        "host": "49.7.253.45",
        "port": 80
    },
    {
        "host": "101.91.40.121",
        "port": 80
    },
    {
        "host": "180.109.192.45",
        "port": 8080
    },
    {
        "host": "180.163.212.180",
        "port": 80
    },
    {
        "host": "183.47.98.11",
        "port": 8080
    }
]